personroles/__init__.py
personroles/mop_role.py
personroles/person.py
personroles/politician_role.py
personroles/resources/__init__.py
personroles/resources/constants.py
personroles/resources/helpers.py
personroles/resources/mop_tinyDB.py
personroles-0.1.8.dist-info/LICENSE
personroles-0.1.8.dist-info/METADATA
personroles-0.1.8.dist-info/WHEEL
personroles-0.1.8.dist-info/top_level.txt
personroles-0.1.8.dist-info/RECORD
