Metadata-Version: 2.1
Name: personroles
Version: 0.1.8
Summary: A set of dataclasses concerning roles of persons and their particulars
Home-page: https://github.com/0LL13/person
Author: Oliver Stapel
Author-email: hardy.ecc95@gmail.com
License: MIT license
Project-URL: Bug Reports, https://github.com/0LL13/person/issues
Project-URL: Source, https://github.com/0LL13/person
Keywords: person,roles
Platform: UNKNOWN
Classifier: Development Status :: 2 - Pre-Alpha
Classifier: Intended Audience :: Developers
Classifier: License :: OSI Approved :: MIT License
Classifier: Natural Language :: English
Classifier: Programming Language :: Python :: 3.8
Classifier: Programming Language :: Python :: Implementation :: CPython
Classifier: Operating System :: POSIX :: Linux
Classifier: Topic :: Other/Nonlisted Topic
Requires-Python: >=3.8
Requires-Dist: beautifulsoup4
Requires-Dist: lxml
Requires-Dist: requests
Requires-Dist: gender-guesser
Requires-Dist: tinydb
Provides-Extra: dev
Requires-Dist: check-manifest ; extra == 'dev'
Provides-Extra: test
Requires-Dist: pytest-cov ; extra == 'test'
